nautobot_api_sandbox_clickui_pkg/__init__.py
nautobot_api_sandbox_clickui_pkg/click_ui.py
nautobot_api_sandbox_clickui_pkg/nautobot_api_sandbox_ui.py
nautobot_api_sandbox_clickui-0.1.0.dist-info/METADATA
nautobot_api_sandbox_clickui-0.1.0.dist-info/WHEEL
nautobot_api_sandbox_clickui-0.1.0.dist-info/RECORD
